llama_index/llms/openai/__init__.py
llama_index/llms/openai/base.py
llama_index/llms/openai/py.typed
llama_index/llms/openai/responses.py
llama_index/llms/openai/utils.py
basejump_llama_index_llms_openai-0.3.39.post1.dist-info/METADATA
basejump_llama_index_llms_openai-0.3.39.post1.dist-info/WHEEL
basejump_llama_index_llms_openai-0.3.39.post1.dist-info/licenses/LICENSE
basejump_llama_index_llms_openai-0.3.39.post1.dist-info/RECORD
