Metadata-Version: 2.4
Name: basejump-llama-index-llms-openai
Version: 0.3.39.post1
Summary: llama-index llms openai integration
Author: llama-index
License-Expression: MIT
License-File: LICENSE
Requires-Python: <4.0,>=3.9
Requires-Dist: basejump-llama-index-core<0.13,>=0.12.17
Requires-Dist: openai==1.76.2
